<?xml version="1.0" encoding="UTF-8"?>
<entity-mappings xmlns="http://xmlns.jcp.org/xml/ns/persistence/orm"
	xmlns:xsi="http://www.w3.org/2001/XMLSchema-instance"
	xsi:schemaLocation="http://xmlns.jcp.org/xml/ns/persistence/orm http://xmlns.jcp.org/xml/ns/persistence/orm_2_1.xsd"
	version="2.1">
	
	<named-native-query name="Vendas.totalPorMes" result-set-mapping="totalPorMesMapping">
		<query>
			SELECT 
			    TO_CHAR(date_trunc('month', data_criacao), 'YYYY/MM') AS mes,
			    COUNT(*) AS total
			FROM 
				venda
			WHERE 
				data_criacao >= CURRENT_DATE - INTERVAL '6 months' AND status = 'EMITIDA'
			GROUP BY 
				date_trunc('month', data_criacao)
			ORDER BY 
				date_trunc('month', data_criacao) DESC;
	    </query>
	</named-native-query>
	
	<named-native-query name="Vendas.porOrigem" result-set-mapping="porOrigemMapping">
		<query>
			SELECT
				to_char(v.data_criacao, 'YYYY/MM') AS mes,
				SUM(CASE WHEN c.origem = 'NACIONAL' THEN i.quantidade ELSE 0 END) AS total_nacional,
				SUM(CASE WHEN c.origem = 'INTERNACIONAL' THEN i.quantidade ELSE 0 END) AS total_internacional
			FROM 
				venda v
			JOIN 
				item_venda i ON i.codigo_venda = v.codigo
			JOIN 
				cerveja c ON i.codigo_cerveja = c.codigo
			WHERE 
				v.data_criacao > NOW() - INTERVAL '6 months' AND v.status = 'EMITIDA'
			GROUP BY 
				to_char(v.data_criacao, 'YYYY/MM')
			ORDER BY 
				mes DESC;
	    </query>
	</named-native-query>
	
	<sql-result-set-mapping name="totalPorMesMapping">
		<constructor-result target-class="com.algaworks.brewer.dto.VendaMes">
			<column name="mes" class="java.lang.String"/>
			<column name="total" class="java.lang.Integer"/>
		</constructor-result>
	</sql-result-set-mapping>
	
	<sql-result-set-mapping name="porOrigemMapping">
		<constructor-result target-class="com.algaworks.brewer.dto.VendaOrigem">
			<column name="mes" class="java.lang.String"/>
			<column name="total_nacional" class="java.lang.Integer"/>
			<column name="total_internacional" class="java.lang.Integer"/>
		</constructor-result>
	</sql-result-set-mapping>
	
</entity-mappings>